capsem/__init__.py
capsem/config_loader.py
capsem/config_loader_test.py
capsem/manager.py
capsem/manager_test.py
capsem/models.py
capsem/tools.py
capsem/tools_test.py
capsem/integrations/__init__.py
capsem/integrations/adk/__init__.py
capsem/integrations/adk/plugin.py
capsem/integrations/adk/runner.py
capsem/policies/__init__.py
capsem/policies/debug_policy.py
capsem/policies/debug_policy_test.py
capsem/policies/pii_policy.py
capsem/policies/pii_policy_test.py
capsem/policies/policy.py
capsem-0.3.2.dist-info/METADATA
capsem-0.3.2.dist-info/WHEEL
capsem-0.3.2.dist-info/RECORD
