Metadata-Version: 2.4
Name: capsem
Version: 0.3.2
Summary: CAPSEM: Contextual Agent Privacy and Security Manager
Requires-Python: >=3.11
Requires-Dist: networkx>=3.5
Requires-Dist: pydantic>=2.11.9
Requires-Dist: python-dotenv>=1.1.1
Requires-Dist: tabulate>=0.9.0
Provides-Extra: adk
Requires-Dist: google-adk>=1.14.1; extra == 'adk'
Requires-Dist: litellm>=1.77.4; extra == 'adk'
Provides-Extra: dev
Requires-Dist: google-genai>=1.38.0; extra == 'dev'
Requires-Dist: ipykernel>=6.30.1; extra == 'dev'
Requires-Dist: nbconvert>=7.16.6; extra == 'dev'
Requires-Dist: openai>=1.109.1; extra == 'dev'
Requires-Dist: pyright>=1.1.405; extra == 'dev'
Requires-Dist: pytest-asyncio>=0.24.0; extra == 'dev'
Requires-Dist: pytest>=8.4.2; extra == 'dev'
Provides-Extra: pii
Requires-Dist: pip>=24.0; extra == 'pii'
Requires-Dist: presidio-analyzer>=2.2.354; extra == 'pii'
Requires-Dist: spacy>=3.8.7; extra == 'pii'
